urdf_to_casadi/__init__.py
urdf_to_casadi/urdfparser.py
urdf_to_casadi/geometry/__init__.py
urdf_to_casadi/geometry/dual_quaternion.py
urdf_to_casadi/geometry/plucker.py
urdf_to_casadi/geometry/quaternion.py
urdf_to_casadi/geometry/transformation_matrix.py
urdf_to_casadi-0.1.1.dist-info/METADATA
urdf_to_casadi-0.1.1.dist-info/WHEEL
urdf_to_casadi-0.1.1.dist-info/entry_points.txt
urdf_to_casadi-0.1.1.dist-info/licenses/LICENSE
urdf_to_casadi-0.1.1.dist-info/RECORD
